{
  "bonusDamage": {
    "lower": 0,
    "upper": 0
  },
  "affectedAttributes": {
    "ArmorMitigation": {
      "lower": 700,
      "upper": 700
    },
    "ArmorMitigationAmount": {
      "lower": 3,
      "upper": 3
    }
  },
  "blackSmithZone": "treacherousPeaks",
  "slug": "ill-fitted-sandals-+3",
  "name": "Ill Fitted Sandals +3",
  "itemDropSound": "sandals",
  "slot": "feet",
  "dieDamage": [],
  "heroStatComplianceDictionary": {},
  "allowedHeroClassList": [
    "Warrior",
    "Ranger",
    "Mage"
  ],
  "imageSlug": "rough-slippers",
  "levelRequirement": 10,
  "type": "ItemTemplate"
}